{"about_roadmap.md":"1qI9rnCQ","about_introduction.md":"cLXaipnK","api_core_composables.md":"Jso_bCR-","about_license.md":"bCObHPkr","guides_development_setup.md":"M_MgHAeh","about_contributing.md":"kNDvhZSW","about_contact.md":"tIYU1qZQ","api_map_globe-mixins.md":"_hCNCPaH","api_map_hooks.md":"nHAqn2tp","api_core_hooks.md":"xHdRnidf","api_map_introduction.md":"DyWnjr1Q","guides_development_deploy.md":"17gOHDNG","guides_development_develop.md":"90BpPbED","api_map_mixins.md":"jSNNAbuR","tools_db.md":"f30L8wY9","tools_infrastructure.md":"L95k5suh","architecture_data-model-view.md":"7n4In_kj","guides_development_configure.md":"gtb3GRUD","tips_app-development.md":"Pl4LzVo1","tips_introduction.md":"mIPxhkcg","tips_mobile-configuration.md":"HlKJ9Z8m","architecture_global-architecture.md":"wAOvZ27b","tools_introduction.md":"CVHXlZ5c","api_core_application.md":"AWFS2nBU","guides_introduction.md":"Sb7FrAG3","index.md":"wR2UgPHC","api_core_mixins.md":"qkTTC_2T","tools_browsers.md":"HLLVqttH","guides_basics_introduction.md":"aQ1SRmWM","tools_cli.md":"hHSUUSlV","architecture_component-view.md":"R3doh1Va","guides_development_publish.md":"YYduP63e","api_map_map-mixins.md":"pcQiuDUF","tools_documentation.md":"0d645ih4","api_map_services.md":"X3f7VeFz","guides_development_test.md":"Jo5v9Lze","architecture_main-concepts.md":"uF7n7Pb0","api_core_services.md":"udXHcl8C","api_introduction.md":"WxS6S7yr","api_core_components.md":"F04eWsu5","api_core_introduction.md":"OHn0UJ2B","architecture_introduction.md":"rfkmVptE","api_map_components.md":"QfIkxMKt","api_map_composables.md":"kPf1FkcF"}
